torchest/__init__.py
torchest/datagen.py
torchest/trainer.py
torchest/utils.py
torchest-0.0.6.dist-info/LICENSE
torchest-0.0.6.dist-info/METADATA
torchest-0.0.6.dist-info/WHEEL
torchest-0.0.6.dist-info/top_level.txt
torchest-0.0.6.dist-info/RECORD
