Metadata-Version: 2.1
Name: torchest
Version: 0.0.6
Summary: Toolbelt for pytorch framework
Home-page: https://github.com/Dvelezs94/torchest
Author: Diego Velez
Author-email: diegovelezs94@gmail.com
License: UNKNOWN
Keywords: python,ai,machine learning,neural network,pytorch,trainer
Platform: UNKNOWN
Classifier: Development Status :: 1 - Planning
Classifier: Intended Audience :: Developers
Classifier: Programming Language :: Python :: 3.10
Classifier: Operating System :: Unix
Classifier: Operating System :: MacOS :: MacOS X
Classifier: Operating System :: Microsoft :: Windows
License-File: LICENSE
Requires-Dist: numpy
Requires-Dist: matplotlib
Requires-Dist: tqdm
Requires-Dist: torch
Requires-Dist: wandb
